LICENSE.txt
LICENSE_SUPPLEMENTAL_DISCLAIMER.txt
MANIFEST.in
README.md
setup.cfg
setup.py
setup_common.py
versioneer.py
cdpcli/__init__.py
cdpcli/_version.py
cdpcli/argparser.py
cdpcli/argprocess.py
cdpcli/arguments.py
cdpcli/auth.py
cdpcli/cdprequest.py
cdpcli/clicommand.py
cdpcli/clidriver.py
cdpcli/client.py
cdpcli/compat.py
cdpcli/completer.py
cdpcli/config.py
cdpcli/configloader.py
cdpcli/credentials.py
cdpcli/docs.py
cdpcli/endpoint.py
cdpcli/exceptions.py
cdpcli/formatter.py
cdpcli/help.py
cdpcli/loader.py
cdpcli/main.py
cdpcli/model.py
cdpcli/paginate.py
cdpcli/paramfile.py
cdpcli/paramformfactor.py
cdpcli/parser.py
cdpcli/retryhandler.py
cdpcli/schema.py
cdpcli/serialize.py
cdpcli/shorthand.py
cdpcli/signers.py
cdpcli/table.py
cdpcli/text.py
cdpcli/textwriter.py
cdpcli/translate.py
cdpcli/utils.py
cdpcli/validate.py
cdpcli/data/_retry.json
cdpcli/data/aliases.yaml
cdpcli/data/cli.json
cdpcli/data/release.txt
cdpcli/data/applications/applications.yaml
cdpcli/data/audit/audit.yaml
cdpcli/data/cloudprivatelinks/cloudprivatelinks.yaml
cdpcli/data/compute/compute.yaml
cdpcli/data/consumption/consumption.yaml
cdpcli/data/datacatalog/datacatalog.yaml
cdpcli/data/datahub/datahub.yaml
cdpcli/data/datalake/datalake.yaml
cdpcli/data/de/de.yaml
cdpcli/data/df/df.yaml
cdpcli/data/dfworkload/dfworkload.yaml
cdpcli/data/drscp/drscp.yaml
cdpcli/data/dw/dw.yaml
cdpcli/data/environments/environments.yaml
cdpcli/data/iam/iam.yaml
cdpcli/data/imagecatalog/imagecatalog.yaml
cdpcli/data/metrics/metrics.yaml
cdpcli/data/ml/ml.yaml
cdpcli/data/notification/notification.yaml
cdpcli/data/opdb/opdb.yaml
cdpcli/data/replicationmanager/replicationmanager.yaml
cdpcli/doc/__init__.py
cdpcli/doc/docstringparser.py
cdpcli/doc/restdoc.py
cdpcli/doc/style.py
cdpcli/examples/configure/_description.rst
cdpcli/examples/configure/get/_description.rst
cdpcli/examples/configure/get/_examples.rst
cdpcli/examples/configure/set/_description.rst
cdpcli/examples/configure/set/_examples.rst
cdpcli_beta.egg-info/PKG-INFO
cdpcli_beta.egg-info/SOURCES.txt
cdpcli_beta.egg-info/dependency_links.txt
cdpcli_beta.egg-info/entry_points.txt
cdpcli_beta.egg-info/requires.txt
cdpcli_beta.egg-info/top_level.txt